pystream/__init__.py
pystream/monthly_simulation.py
pystream/plotting.py
pystream/utils.py
pystream_model-0.0.1.dist-info/LICENSE
pystream_model-0.0.1.dist-info/METADATA
pystream_model-0.0.1.dist-info/WHEEL
pystream_model-0.0.1.dist-info/top_level.txt
pystream_model-0.0.1.dist-info/RECORD
