Metadata-Version: 2.1
Name: pystream-model
Version: 0.0.1
Summary: Python STREAM hydrological rainfall-runoff model
Home-page: https://github.com/martibosch/pystream
Author: Martí Bosch
Author-email: marti.bosch@epfl.ch
License: GPL-3.0
Platform: UNKNOWN
Classifier: License :: OSI Approved :: GNU Lesser General Public License v3 (LGPLv3)
Classifier: Programming Language :: Python
Classifier: Programming Language :: Python :: 3
Classifier: Programming Language :: Python :: 3.6
Requires-Dist: matplotlib (>=2.2)
Requires-Dist: numpy (>=1.13)
Requires-Dist: rasterio (>=1.0.0)
Requires-Dist: richdem (>=0.3.4)
Requires-Dist: xarray (>=0.11.0)
